piperoni/__init__.py
piperoni/__version__.py
piperoni/utils.py
piperoni/operators/__init__.py
piperoni/operators/base.py
piperoni/operators/cast_operator.py
piperoni/operators/pandas_operators.py
piperoni/operators/passthrough_operator.py
piperoni/operators/pipe.py
piperoni/operators/pipeline.py
piperoni/operators/transform_operator.py
piperoni/operators/analyze/__init__.py
piperoni/operators/analyze/comparer.py
piperoni/operators/extract/__init__.py
piperoni/operators/extract/extract_file/__init__.py
piperoni/operators/extract/extract_file/base.py
piperoni/operators/extract/extract_file/csv_.py
piperoni/operators/extract/extract_file/excel.py
piperoni/operators/extract/extract_file/json_.py
piperoni/operators/load/__init__.py
piperoni/operators/load/checkpoint.py
piperoni/operators/transform/__init__.py
piperoni/operators/transform/assign_uids_operator.py
piperoni/operators/transform/featurize/__init__.py
piperoni/operators/transform/featurize/featurizer.py
piperoni/operators/transform/transform_name/__init__.py
piperoni/operators/transform/transform_name/header_map.py
piperoni/operators/transform/transform_value/__init__.py
piperoni/operators/transform/transform_value/value_transformers.py
piperoni-3.0.7.dist-info/LICENSE
piperoni-3.0.7.dist-info/METADATA
piperoni-3.0.7.dist-info/WHEEL
piperoni-3.0.7.dist-info/top_level.txt
piperoni-3.0.7.dist-info/RECORD
