Metadata-Version: 2.1
Name: piperoni
Version: 3.0.7
Summary: Citrine Informatics ETL pipeline
Home-page: http://github.com/CitrineInformatics/piperoni
Author: Citrine Informatics
License: UNKNOWN
Platform: UNKNOWN
Classifier: Programming Language :: Python :: 3
Classifier: Programming Language :: Python :: 3.7
Classifier: Programming Language :: Python :: 3.8
Requires-Dist: pyyaml (<6,>=5.4)
Requires-Dist: pandas (<2,>=1.2)
Requires-Dist: xlrd (==1.2.0)
Requires-Dist: dagre-py (==0.1.6)
